{
    "aka": [],
    "sid": "tt0020366",
    "name": "Say It with Songs",
    "site": "imdb",
    "year": "1930",
    "@type": "Movie",
    "genre": [
        "Drama",
        "Musical"
    ],
    "actors": [
        {
            "url": "https://www.imdb.com/name/nm0427231/",
            "name": "Al Jolson"
        },
        {
            "url": "https://www.imdb.com/name/nm0497109/",
            "name": "Davey Lee"
        },
        {
            "url": "https://www.imdb.com/name/nm0633260/",
            "name": "Marian Nixon"
        }
    ],
    "critic": 2,
    "poster": "https://m.media-amazon.com/images/M/MV5BMTUzNzE1MzAxN15BMl5BanBnXkFtZTgwMTYzMDEwMzE@._V1_.jpg",
    "details": {
        "Language": [
            "English"
        ],
        "Release date": [
            "January 24, 1930 (Ireland)"
        ],
        "Also known as": [
            "Onu Şarkı İle Söyle!"
        ],
        "Country of origin": [
            "United States"
        ],
        "Filming locations": [
            "Warner Brothers Burbank Studios - 4000 Warner Boulevard, Burbank, California, USA"
        ],
        "Production company": [
            "Warner Bros."
        ]
    },
    "reviews": 11,
    "creators": [
        {
            "url": "https://www.imdb.com/name/nm0953123/",
            "name": "Darryl F. Zanuck"
        },
        {
            "url": "https://www.imdb.com/name/nm0309567/",
            "name": "Harvey Gates"
        },
        {
            "url": "https://www.imdb.com/name/nm0413711/",
            "name": "Joseph Jackson"
        }
    ],
    "duration": "PT1H35M",
    "keywords": [
        "1920s",
        "radio singer",
        "pathos",
        "grief",
        "song"
    ],
    "directors": [
        {
            "url": "https://www.imdb.com/name/nm0045800/",
            "name": "Lloyd Bacon"
        }
    ],
    "imdb_link": "https://www.imdb.com/title/tt0020366/",
    "metascore": null,
    "imdb_votes": 166,
    "popularity": 0,
    "description": "Joe Lane kills another man in a fistfight after learning that the man has made improper advances towards his wife. Joe goes to prison for the murder. When Joe gets out of prison, he visits his son &quot;Little Pal&quot; at school. Little Pa...",
    "imdb_rating": "4.9/10 from 166 users",
    "release_date": [],
    "contentRating": "Passed",
    "datePublished": "1930-01-24",
    "imdb_rating_average": 4.9,
    "update_at": "2025-06-01T19:00:25"
}