{
    "aka": [],
    "sid": "tt0204670",
    "name": "Takarashima sendai",
    "site": "imdb",
    "year": "1956",
    "@type": "Movie",
    "genre": [
        "Comedy",
        "Fantasy"
    ],
    "actors": [
        {
            "url": "https://www.imdb.com/name/nm4085103/",
            "name": "Ryô Daitô"
        },
        {
            "url": "https://www.imdb.com/name/nm0257951/",
            "name": "Ken&apos;ichi Enomoto"
        },
        {
            "url": "https://www.imdb.com/name/nm6449036/",
            "name": "Keiko Fukami"
        }
    ],
    "critic": 0,
    "poster": "https://m.media-amazon.com/images/M/MV5BYThhMGM0NjItNjQyYy00ZWJmLWI1MTEtY2I1Nzc1ZjViZTg3XkEyXkFqcGc@._V1_.jpg",
    "details": {
        "Language": [
            "Japanese"
        ],
        "Release date": [
            "July 20, 1956 (Japan)"
        ],
        "Also known as": [
            "Excursion to Treasure Isle"
        ],
        "Official site": [
            "jmdb site - http://www.jmdb.ne.jp/1956/cf003270.htm"
        ],
        "Country of origin": [
            "Japan"
        ],
        "Production company": [
            "Toei Company"
        ]
    },
    "reviews": 0,
    "creators": [
        {
            "url": "https://www.imdb.com/name/nm1834334/",
            "name": "Tatsuo Nakada"
        },
        {
            "url": "https://www.imdb.com/name/nm0644823/",
            "name": "Hideo Oguni"
        },
        {
            "url": "https://www.imdb.com/name/nm1964241/",
            "name": "Yutaka Okada"
        }
    ],
    "duration": "PT1H27M",
    "keywords": [
        ""
    ],
    "directors": [
        {
            "url": "https://www.imdb.com/name/nm14597767/",
            "name": "Tsuneo Kobayashi"
        }
    ],
    "imdb_link": "https://www.imdb.com/title/tt0204670/",
    "metascore": null,
    "imdb_votes": 12,
    "popularity": 0,
    "description": null,
    "imdb_rating": "5.9/10 from 12 users",
    "release_date": [],
    "contentRating": null,
    "datePublished": "1956-07-20",
    "imdb_rating_average": 5.9,
    "update_at": "2025-07-01T23:35:12"
}