{
    "aka": [],
    "sid": "tt0369910",
    "name": "Secret Santa",
    "site": "imdb",
    "year": "2003",
    "@type": "Movie",
    "genre": [
        "Drama",
        "Family"
    ],
    "actors": [
        {
            "url": "https://www.imdb.com/name/nm0001259/",
            "name": "Jennie Garth"
        },
        {
            "url": "https://www.imdb.com/name/nm0248692/",
            "name": "Steven Eckholdt"
        },
        {
            "url": "https://www.imdb.com/name/nm0501534/",
            "name": "Charles Robinson"
        }
    ],
    "critic": 3,
    "poster": "https://m.media-amazon.com/images/M/MV5BNmU2NDQ5ZTctNDkyNi00YTM5LWJiYTEtMzQ2ZTVjMzI2OGIzXkEyXkFqcGc@._V1_.jpg",
    "details": {
        "Language": [
            "English"
        ],
        "Release date": [
            "December 14, 2003 (United States)"
        ],
        "Also known as": [
            "Таємничий Санта"
        ],
        "Country of origin": [
            "United States"
        ],
        "Filming locations": [
            "Los Angeles, California, USA"
        ],
        "Production companies": [
            "Madison Avenue Productions Inc.",
            "The Polson Company"
        ]
    },
    "reviews": 9,
    "creators": [
        {
            "url": "https://www.imdb.com/name/nm0689848/",
            "name": "Beth Polson"
        },
        {
            "url": "https://www.imdb.com/name/nm1086699/",
            "name": "Robert Tate Miller"
        }
    ],
    "duration": "PT1H40M",
    "keywords": [
        "christmas"
    ],
    "directors": [
        {
            "url": "https://www.imdb.com/name/nm0058018/",
            "name": "Ian Barry"
        }
    ],
    "imdb_link": "https://www.imdb.com/title/tt0369910/",
    "metascore": null,
    "imdb_votes": 680,
    "popularity": 0,
    "description": "Newspaper reporter Rebecca Chandler, who feels she got no fair chance to prove her worth in her three years career, looks forward to a Hawaian holiday with her fiancé Ryan, but instead of a ring he brings her- walking orders, he f...",
    "imdb_rating": "6/10 from 680 users",
    "release_date": [],
    "contentRating": null,
    "datePublished": "2003-12-14",
    "imdb_rating_average": 6,
    "update_at": "2025-06-13T18:26:20"
}