{
    "aka": [],
    "sid": "tt13286188",
    "name": "Good Grief",
    "site": "imdb",
    "@type": "Movie",
    "genre": [
        "Comedy",
        "Drama"
    ],
    "actors": [
        {
            "url": "https://www.imdb.com/name/nm3320276/",
            "name": "Emily Rued"
        },
        {
            "url": "https://www.imdb.com/name/nm0926615/",
            "name": "Johnny Whitworth"
        },
        {
            "url": "https://www.imdb.com/name/nm0857201/",
            "name": "Brynn Thayer"
        }
    ],
    "critic": 0,
    "poster": "https://m.media-amazon.com/images/M/MV5BMmRmYTA3MjQtYTBiZC00YTkxLWFlNmMtZWNmNmZlYWQxYmE4XkEyXkFqcGc@._V1_.jpg",
    "details": {
        "Country of origin": [
            "United States"
        ],
        "Production companies": [
            "Maua Media",
            "Nimby Pictures"
        ]
    },
    "reviews": 0,
    "creators": [
        {
            "url": "https://www.imdb.com/name/nm3320276/",
            "name": "Emily Rued"
        }
    ],
    "duration": null,
    "keywords": [
        "mother"
    ],
    "directors": [
        {
            "url": "https://www.imdb.com/name/nm5794274/",
            "name": "Jaclyn Bethany"
        }
    ],
    "imdb_link": "https://www.imdb.com/title/tt13286188/",
    "metascore": null,
    "imdb_votes": 0,
    "popularity": 0,
    "description": "After her mother suddenly dies, a pushover painter must battle through the opinions and expectations of family, &quot;friends,&quot; and a toxic boyfriend to plan her funeral.",
    "imdb_rating": "0/10 from 0 users",
    "release_date": [],
    "contentRating": null,
    "datePublished": null,
    "imdb_rating_average": 0,
    "update_at": "2025-03-01T08:28:04"
}