{
    "aka": [],
    "sid": "tt32468632",
    "name": "Confluence",
    "site": "imdb",
    "year": "2024",
    "@type": "TVSeries",
    "genre": [
        "Documentary"
    ],
    "critic": 0,
    "poster": "https://m.media-amazon.com/images/M/MV5BNmQ4MGJjYzctNTFhMy00Y2I0LWEyZmUtNmQzZTM3Mjc3NDVhXkEyXkFqcGc@._V1_.jpg",
    "details": {
        "Languages": [
            "English",
            "French"
        ],
        "Release date": [
            "July 12, 2024 (United States)"
        ],
        "Official site": [
            "Official website - http://www.confluence.tv/"
        ],
        "Country of origin": [
            "United States"
        ],
        "Production company": [
            "Center for New American Media (CNAM)"
        ]
    },
    "reviews": 0,
    "creators": [],
    "duration": null,
    "keywords": [
        "tv mini series"
    ],
    "imdb_link": "https://www.imdb.com/title/tt32468632/",
    "metascore": null,
    "imdb_votes": 0,
    "popularity": 0,
    "description": "CONFLUENCE is a three-part series which explores the many ways art, science, and technology come together to spark human creativity, featuring some of the boldest innovators in art, music, and tech.",
    "imdb_rating": "0/10 from 0 users",
    "release_date": [],
    "contentRating": null,
    "datePublished": "2024-07-12",
    "imdb_rating_average": 0,
    "update_at": "2025-11-03T15:00:11"
}