{
    "aka": [],
    "sid": "tt6436888",
    "name": "The Cage Fighter",
    "site": "imdb",
    "year": "2017",
    "@type": "Movie",
    "genre": [
        "Documentary",
        "Action",
        "Drama"
    ],
    "actors": [
        {
            "url": "https://www.imdb.com/name/nm8718186/",
            "name": "Vernon Beach"
        },
        {
            "url": "https://www.imdb.com/name/nm8718184/",
            "name": "Callie Carman"
        },
        {
            "url": "https://www.imdb.com/name/nm8811977/",
            "name": "Delanee Carman"
        }
    ],
    "critic": 8,
    "poster": "https://m.media-amazon.com/images/M/MV5BMTg5MTYxOTYxMl5BMl5BanBnXkFtZTgwMTY4MjQ2NDM@._V1_.jpg",
    "details": {
        "Language": [
            "English"
        ],
        "Release date": [
            "March 2, 2017 (United States)"
        ],
        "Also known as": [
            "铁笼斗士"
        ],
        "Official site": [
            "Official site - http://greywaterfilm.com/"
        ],
        "Country of origin": [
            "United States"
        ],
        "Filming locations": [
            "Washington, USA"
        ],
        "Production companies": [
            "Cinereach",
            "Lineage Films",
            "The Filmmaker Fund"
        ]
    },
    "reviews": 5,
    "creators": [
        {
            "url": "https://www.imdb.com/name/nm2090073/",
            "name": "David Teague"
        },
        {
            "url": "https://www.imdb.com/name/nm1466538/",
            "name": "Jeff Unay"
        }
    ],
    "duration": "PT1H21M",
    "keywords": [
        "fight"
    ],
    "directors": [
        {
            "url": "https://www.imdb.com/name/nm1466538/",
            "name": "Jeff Unay"
        }
    ],
    "imdb_link": "https://www.imdb.com/title/tt6436888/",
    "metascore": 71,
    "imdb_votes": 276,
    "popularity": 0,
    "description": "A blue-collar family man breaks the promise he&apos;d made to never fight again. Now forty years old, with a wife and four children who need him, Joe Carman risks everything to go back into the fighting cage and come to terms with his ...",
    "imdb_rating": "6.1/10 from 276 users",
    "release_date": [],
    "contentRating": "Unrated",
    "datePublished": "2017-03-02",
    "imdb_rating_average": 6.1,
    "update_at": "2025-02-11T08:17:08"
}