{
    "sid": "1095364",
    "name": "泰德·格林",
    "site": "douban_celebrity",
    "roles": [
        "演员",
        "配音"
    ],
    "awards": [],
    "gender": "男",
    "poster": "https://img1.doubanio.com/view/celebrity/m/public/p26573.jpg",
    "imdb_id": "nm0311811",
    "name_en": "Ted Gehring",
    "name_full": "泰德·格林 Ted Gehring",
    "birth_date": "1929年4月6日",
    "birth_place": "美国,亚利桑那州,比斯比",
    "last_movies": [
        {
            "id": 5049786,
            "year": "1983",
            "cover": "https://img1.doubanio.com/view/photo/l_ratio_poster/public/p2423130520.jpg",
            "title": "塌桥大灾难",
            "release": 1
        },
        {
            "id": 5049586,
            "year": "1984",
            "cover": "https://img1.doubanio.com/view/photo/l_ratio_poster/public/p2884494595.jpg",
            "title": "冠军之队",
            "release": 1
        },
        {
            "id": 5049541,
            "year": "1984",
            "cover": "https://img1.doubanio.com/view/photo/l_ratio_poster/public/p2625842269.jpg",
            "title": "杰茜",
            "release": 1
        },
        {
            "id": 5049343,
            "year": "1984",
            "cover": "https://img1.doubanio.com/cuphead/movie-static/pics/movie_default_medium.png",
            "title": "Gone Are the Dayes",
            "release": 1
        },
        {
            "id": 3930020,
            "year": "1986",
            "cover": "https://img1.doubanio.com/view/photo/l_ratio_poster/public/p2876121901.jpg",
            "title": "外星恋",
            "release": 1
        },
        {
            "id": 2076320,
            "year": "1986",
            "cover": "https://img1.doubanio.com/view/photo/l_ratio_poster/public/p2462359821.jpg",
            "title": "辩护律师",
            "release": 1
        },
        {
            "id": 2070003,
            "year": "1983",
            "cover": "https://img1.doubanio.com/view/photo/l_ratio_poster/public/p2173746008.jpg",
            "title": "侠骨柔情 第一季",
            "release": 1
        },
        {
            "id": 1857872,
            "year": "1984",
            "cover": "https://img1.doubanio.com/view/photo/l_ratio_poster/public/p2228203109.jpg",
            "title": "神探亨特",
            "release": 1
        },
        {
            "id": 1299455,
            "year": "1986",
            "cover": "https://img1.doubanio.com/view/photo/l_ratio_poster/public/p2504801766.jpg",
            "title": "虎胆小子",
            "release": 1
        },
        {
            "id": 1296783,
            "year": "1986",
            "cover": "https://img1.doubanio.com/view/photo/l_ratio_poster/public/p2178582515.jpg",
            "title": "墨菲罗曼史",
            "release": 1
        }
    ],
    "introduction": "暂无",
    "name_more_cn": [],
    "personage_id": "27301149",
    "family_member": [],
    "celebrity_link": "https://movie.douban.com/celebrity/1095364",
    "personage_link": "https://www.douban.com/personage/27301149/",
    "property_other": [
        {
            "label": "去世日期",
            "value": "2000年9月28日"
        }
    ],
    "name_more_other": [],
    "update_at": "2025-02-04T01:12:05"
}