{
    "sid": "1303614",
    "name": "Michelle Jones",
    "site": "douban_celebrity",
    "roles": [
        "演员",
        "制片人"
    ],
    "awards": [],
    "gender": "",
    "poster": "https://img1.doubanio.com/f/vendors/8dd0c794499fe925ae2ae89ee30cd225750457b4/pics/personage-default-medium.png",
    "imdb_id": "nm1113231",
    "name_en": "",
    "name_full": "Michelle Jones",
    "birth_date": "",
    "birth_place": "",
    "last_movies": [
        {
            "id": 37215366,
            "year": "2025",
            "cover": "https://img1.doubanio.com/cuphead/movie-static/pics/movie_default_medium.png",
            "title": "Pescador",
            "release": 0
        },
        {
            "id": 35474193,
            "year": "2001",
            "cover": "https://img1.doubanio.com/view/photo/l_ratio_poster/public/p2652524955.jpg",
            "title": "Separate Ways",
            "release": 1
        },
        {
            "id": 30384735,
            "year": "2019",
            "cover": "https://img1.doubanio.com/view/photo/l_ratio_poster/public/p2540637780.jpg",
            "title": "杜立巴",
            "release": 1
        },
        {
            "id": 5143690,
            "year": "2000",
            "cover": "https://img1.doubanio.com/cuphead/movie-static/pics/movie_default_medium.png",
            "title": "Warpath",
            "release": 1
        },
        {
            "id": 5111059,
            "year": "1995",
            "cover": "https://img1.doubanio.com/view/photo/l_ratio_poster/public/p2891740323.jpg",
            "title": "Minor Adjustments",
            "release": 1
        }
    ],
    "introduction": "暂无",
    "name_more_cn": [],
    "personage_id": "27531894",
    "family_member": [],
    "celebrity_link": "https://movie.douban.com/celebrity/1303614",
    "personage_link": "https://www.douban.com/personage/27531894/",
    "property_other": [],
    "name_more_other": [],
    "update_at": "2025-03-12T10:13:24"
}