{
    "aka": [
        "A LOVE-FORSAKEN CORNER"
    ],
    "sid": "1759783",
    "cast": [
        {
            "url": "/celebrity/1009141/",
            "name": "沈丹萍 Danping Shen",
            "@type": "Person"
        },
        {
            "url": "/celebrity/1305422/",
            "name": "贺小书 Xiaoshu He",
            "@type": "Person"
        },
        {
            "url": "/celebrity/1324539/",
            "name": "杨海莲 Hailian Yang",
            "@type": "Person"
        },
        {
            "url": "/celebrity/1336229/",
            "name": "张世会 Shihui Zhang",
            "@type": "Person"
        },
        {
            "url": "/celebrity/1357308/",
            "name": "许瑞萍 Ruiping Xu",
            "@type": "Person"
        },
        {
            "url": "/celebrity/1325189/",
            "name": "李国华 Guohua Li",
            "@type": "Person"
        },
        {
            "url": "/celebrity/1328118/",
            "name": "金迪 Di Jin",
            "@type": "Person"
        },
        {
            "url": "/celebrity/1362550/",
            "name": "郭琦 Qi Guo",
            "@type": "Person"
        },
        {
            "url": "/celebrity/1464326/",
            "name": "夏峰 Feng Xia",
            "@type": "Person"
        },
        {
            "url": "/celebrity/1322554/",
            "name": "毕克 Ke Bi",
            "@type": "Person"
        }
    ],
    "site": "douban",
    "tags": [],
    "year": "",
    "genre": [
        "剧情"
    ],
    "awards": "　　第2届中国电影金鸡奖(1982)\n　　最佳编剧 张弦\n　　最佳女配角 贺小书\n　　最佳美术(提名)\n　　最佳服装(提名)\n\n",
    "poster": "https://img1.doubanio.com/view/photo/l_ratio_poster/public/p2700298863.jpg",
    "region": [
        "中国大陆"
    ],
    "writer": [
        {
            "url": "/celebrity/1328145/",
            "name": "张弦 Xian Zhang",
            "@type": "Person"
        }
    ],
    "imdb_id": "tt0342095",
    "director": [
        {
            "url": "/celebrity/1409127/",
            "name": "张其 Qi Zhang",
            "@type": "Person"
        },
        {
            "url": "/celebrity/1322006/",
            "name": "李亚林 Yalin Li",
            "@type": "Person"
        }
    ],
    "duration": "91分钟",
    "episodes": "",
    "language": [
        "汉语普通话"
    ],
    "playdate": [],
    "imdb_link": "https://www.imdb.com/title/tt0342095/",
    "imdb_votes": 33,
    "this_title": [
        "被爱情遗忘的角落"
    ],
    "douban_link": "https://movie.douban.com/subject/1759783/",
    "imdb_rating": "7.6/10 from 33 users",
    "trans_title": [
        "A LOVE-FORSAKEN CORNER"
    ],
    "douban_votes": "2041",
    "introduction": "农民沈山旺（李国华 饰）有两个女儿，存妮（杨海莲 饰）和荒妹（沈丹萍 饰）。她们生活在物质和精神极其贫困的年代。在那个封建意识和极左猖獗的角落，爱情是绝不允许的。当存妮和同村的小豹子（张潮 饰）野地约会被“捉奸”，存妮含看无限羞愤跳塘自杀。憨厚质朴的小豹子则被控为“强奸致死人命罪”锒铛入狱。这给妹妹荒妹的心灵带来很大的创伤。和她青梅竹马的小伙子许荣树（张世会 饰）复员回到家乡，看到家乡依然贫穷落后，就努力想办法改变故乡的贫穷面貌。荒妹十分仰慕荣树，但一想到姐姐的悲惨命运，阴影又袭上她的心头。这时侯，她又看到本村青年英娣（杨秋复 饰）和二槐（夏峰 饰）自由恋爱，而英娣娘（金迪 饰）却不答应，让她同一个素不相识的男人结了婚，生活的非常不幸。目睹此情此景，荒妹的内心更加矛盾了，她该怎么办呢......",
    "chinese_title": "被爱情遗忘的角落",
    "douban_rating": "7.6/10 from 2041 users",
    "foreign_title": "",
    "imdb_rating_average": 7.6,
    "douban_rating_average": "7.6",
    "update_at": "2024-06-21T17:00:13"
}