{
    "aka": [
        "Neighborhood Treasures 4"
    ],
    "sid": "26967945",
    "cast": [
        {
            "url": "/celebrity/1038992/",
            "name": "森美 Sammy Leung",
            "@type": "Person"
        },
        {
            "url": "/celebrity/1219964/",
            "name": "阮小仪 Kitty Yuen",
            "@type": "Person"
        },
        {
            "url": "/celebrity/1386668/",
            "name": "李伟健 Kim Li",
            "@type": "Person"
        },
        {
            "url": "/celebrity/1357017/",
            "name": "陈亭嘉 Kaka Chan",
            "@type": "Person"
        },
        {
            "url": "/celebrity/1315854/",
            "name": "乔宝宝 Gill Mohindepaul Singh",
            "@type": "Person"
        },
        {
            "url": "/celebrity/1356346/",
            "name": "张美妮 Meini Cheung",
            "@type": "Person"
        },
        {
            "url": "/celebrity/1337844/",
            "name": "安德尊 Anderson Junior",
            "@type": "Person"
        },
        {
            "url": "/celebrity/1042796/",
            "name": "陈炜 Alice Chan",
            "@type": "Person"
        },
        {
            "url": "/celebrity/1398340/",
            "name": "宋芝龄 Sung Chih Ling",
            "@type": "Person"
        },
        {
            "url": "/celebrity/1409957/",
            "name": "朱汇林 Chu Hui-Lin",
            "@type": "Person"
        },
        {
            "url": "/celebrity/1274449/",
            "name": "许绍雄 Siu-Hung Hui",
            "@type": "Person"
        },
        {
            "url": "/celebrity/1043369/",
            "name": "姚子羚 Elaine Yiu",
            "@type": "Person"
        },
        {
            "url": "/celebrity/1023827/",
            "name": "薛凯琪 Fiona Sit",
            "@type": "Person"
        },
        {
            "url": "/celebrity/1275779/",
            "name": "周柏豪  Pakho Chau",
            "@type": "Person"
        },
        {
            "url": "/celebrity/1317145/",
            "name": "张景淳 Stanley Cheung King Shun",
            "@type": "Person"
        },
        {
            "url": "/celebrity/1275715/",
            "name": "朱咪咪 Mimi Chu",
            "@type": "Person"
        },
        {
            "url": "/celebrity/1274905/",
            "name": "黎诺懿 Lok-Yi Lai",
            "@type": "Person"
        },
        {
            "url": "/celebrity/1275781/",
            "name": "朱璇 Oceane Zhu",
            "@type": "Person"
        },
        {
            "url": "/celebrity/1355198/",
            "name": "张嘉儿 Kayi Cheung",
            "@type": "Person"
        },
        {
            "url": "/celebrity/1317182/",
            "name": "金刚 Kong King",
            "@type": "Person"
        },
        {
            "url": "/celebrity/1354757/",
            "name": "陈庭欣 Toby Chan",
            "@type": "Person"
        },
        {
            "url": "/celebrity/1326933/",
            "name": "庄思明 Lisa Chong",
            "@type": "Person"
        },
        {
            "url": "/celebrity/1315587/",
            "name": "苟芸慧 Christine Kuo",
            "@type": "Person"
        },
        {
            "url": "/celebrity/1251513/",
            "name": "李亚男 Leanne Lee",
            "@type": "Person"
        },
        {
            "url": "/celebrity/1318964/",
            "name": "吴家乐 Carlo Ng Ka-Lok",
            "@type": "Person"
        },
        {
            "url": "/celebrity/1318175/",
            "name": "叶翠翠 Tracy Ip",
            "@type": "Person"
        },
        {
            "url": "/celebrity/1322357/",
            "name": "梁嘉琪 Kaki Leung",
            "@type": "Person"
        },
        {
            "url": "/celebrity/1333251/",
            "name": "温家伟 Alan Wan",
            "@type": "Person"
        },
        {
            "url": "/celebrity/1044122/",
            "name": "郭政鸿 Jing-hung Kwok",
            "@type": "Person"
        },
        {
            "url": "/celebrity/1316304/",
            "name": "杨秀惠 Vivien Yeo",
            "@type": "Person"
        },
        {
            "url": "/celebrity/1320111/",
            "name": "邓梓峰 Chi-Fung Tang",
            "@type": "Person"
        },
        {
            "url": "/celebrity/1323010/",
            "name": "岑丽香 Eliza Sam",
            "@type": "Person"
        },
        {
            "url": "/celebrity/1353241/",
            "name": "李绮雯 Yee-Man Lee",
            "@type": "Person"
        },
        {
            "url": "/celebrity/1327655/",
            "name": "吴业坤 Ng Yip Kwan",
            "@type": "Person"
        },
        {
            "url": "/celebrity/1317300/",
            "name": "何傲儿 Lily Ho",
            "@type": "Person"
        },
        {
            "url": "/celebrity/1321628/",
            "name": "张慧雯 Candy Chang",
            "@type": "Person"
        },
        {
            "url": "/celebrity/1314568/",
            "name": "吕慧仪 Konnie Lui",
            "@type": "Person"
        },
        {
            "url": "/celebrity/1317316/",
            "name": "王君馨 Grace Wong",
            "@type": "Person"
        },
        {
            "url": "/celebrity/1328778/",
            "name": "关婉珊 Kimmy Kwan",
            "@type": "Person"
        },
        {
            "url": "/celebrity/1364174/",
            "name": "许廷铿 Alfred Hui",
            "@type": "Person"
        },
        {
            "url": "/celebrity/1007512/",
            "name": "郑欣宜 Joyce Cheng",
            "@type": "Person"
        },
        {
            "url": "/celebrity/1322710/",
            "name": "郑诗君 Sze-kwan Cheng",
            "@type": "Person"
        },
        {
            "url": "/celebrity/1275662/",
            "name": "陆永 Wing-kuen Luk",
            "@type": "Person"
        },
        {
            "url": "/celebrity/1357343/",
            "name": "胡鸿钧 Hubert Wu",
            "@type": "Person"
        },
        {
            "url": "/celebrity/1340818/",
            "name": "吴若希 Jinny Ng",
            "@type": "Person"
        },
        {
            "url": "/celebrity/1340624/",
            "name": "胡诺言 Jack Wu Lok Yin",
            "@type": "Person"
        },
        {
            "url": "/celebrity/1347884/",
            "name": "陈琪 June Chan",
            "@type": "Person"
        },
        {
            "url": "/celebrity/1314773/",
            "name": "洪天明 Timmy Hung Tin-Ming",
            "@type": "Person"
        },
        {
            "url": "/celebrity/1369528/",
            "name": "周家蔚 Janet Chow",
            "@type": "Person"
        },
        {
            "url": "/celebrity/1048705/",
            "name": "邓健泓 Patrick Tang",
            "@type": "Person"
        },
        {
            "url": "/celebrity/1314777/",
            "name": "龚嘉欣 Katy Kung",
            "@type": "Person"
        },
        {
            "url": "/celebrity/1104138/",
            "name": "江欣燕 Elvina Kong",
            "@type": "Person"
        },
        {
            "url": "/celebrity/1386291/",
            "name": "罗孝勇 Sheldon Lo",
            "@type": "Person"
        },
        {
            "url": "/celebrity/1317618/",
            "name": "林欣彤 Mag Lam",
            "@type": "Person"
        },
        {
            "url": "/celebrity/1274238/",
            "name": "王祖蓝 Cho-lam Wong",
            "@type": "Person"
        },
        {
            "url": "/celebrity/1385914/",
            "name": "冯允谦 Jay Fung",
            "@type": "Person"
        },
        {
            "url": "/celebrity/1326852/",
            "name": "林夏薇 Rosina Lin",
            "@type": "Person"
        },
        {
            "url": "/celebrity/1043737/",
            "name": "袁伟豪 Benjamin Yuen",
            "@type": "Person"
        },
        {
            "url": "/celebrity/1373611/",
            "name": "黄得生 Ocean Wong",
            "@type": "Person"
        },
        {
            "url": "/celebrity/1145127/",
            "name": "商天娥 Tin-Ngoh Seung",
            "@type": "Person"
        },
        {
            "url": "/celebrity/1316306/",
            "name": "李思欣 Charmaine Li",
            "@type": "Person"
        },
        {
            "url": "/celebrity/1314649/",
            "name": "陈奂仁 Hanjin Tan",
            "@type": "Person"
        },
        {
            "url": "/celebrity/1316094/",
            "name": "高海宁 Samantha Ko",
            "@type": "Person"
        },
        {
            "url": "/celebrity/1384755/",
            "name": "宋熙年 Sarah Song",
            "@type": "Person"
        },
        {
            "url": "/celebrity/1315890/",
            "name": "沈卓盈 Jess Shum Cheuk Ying",
            "@type": "Person"
        },
        {
            "url": "/celebrity/1314338/",
            "name": "徐淑敏 Suki Chui",
            "@type": "Person"
        },
        {
            "url": "/celebrity/1316305/",
            "name": "马菀迎 Sire Ma",
            "@type": "Person"
        },
        {
            "url": "/celebrity/1319760/",
            "name": "翟锋 William Chak",
            "@type": "Person"
        },
        {
            "url": "/celebrity/1313729/",
            "name": "敖嘉年 Kanin Ngo",
            "@type": "Person"
        },
        {
            "url": "/celebrity/1275719/",
            "name": "江若琳 Elanne Kwong",
            "@type": "Person"
        },
        {
            "url": "/celebrity/1275266/",
            "name": "梁竞徽 Oscar Leung",
            "@type": "Person"
        },
        {
            "url": "/celebrity/1334783/",
            "name": "李璧琦 Becky Lee",
            "@type": "Person"
        },
        {
            "url": "/celebrity/1321627/",
            "name": "陈智燊 Jason Chan",
            "@type": "Person"
        },
        {
            "url": "/celebrity/1307051/",
            "name": "萧正楠 Edwin Siu",
            "@type": "Person"
        },
        {
            "url": "/celebrity/1319138/",
            "name": "乐瞳 Cilla Kung",
            "@type": "Person"
        },
        {
            "url": "/celebrity/1227332/",
            "name": "胡定欣 Nancy Wu Ting-yan",
            "@type": "Person"
        },
        {
            "url": "/celebrity/1274580/",
            "name": "麦长青 Cheung-Ching Mak",
            "@type": "Person"
        },
        {
            "url": "/celebrity/1314782/",
            "name": "蒋家旻 Angel Chiang",
            "@type": "Person"
        },
        {
            "url": "/celebrity/1321314/",
            "name": "罗钧满 Ronald Law",
            "@type": "Person"
        },
        {
            "url": "/celebrity/1274951/",
            "name": "阮兆祥 Louis Yuen",
            "@type": "Person"
        },
        {
            "url": "/celebrity/1274760/",
            "name": "贾晓晨 J.J. Jia",
            "@type": "Person"
        },
        {
            "url": "/celebrity/1245590/",
            "name": "马国明 Kwok-Ming Ma",
            "@type": "Person"
        },
        {
            "url": "/celebrity/1315865/",
            "name": "江美仪 Elena Kong",
            "@type": "Person"
        },
        {
            "url": "/celebrity/1316282/",
            "name": "狄易达 Tat Dik",
            "@type": "Person"
        },
        {
            "url": "/celebrity/1323262/",
            "name": "张秀文 Sammi Cheung",
            "@type": "Person"
        }
    ],
    "site": "douban",
    "tags": [],
    "year": "2012",
    "genre": [
        "真人秀"
    ],
    "awards": "",
    "poster": "https://img1.doubanio.com/view/photo/l_ratio_poster/public/p2533685171.jpg",
    "region": [
        "中国香港"
    ],
    "writer": [],
    "director": [],
    "duration": "45分鐘",
    "episodes": "14",
    "language": [
        "粤语"
    ],
    "playdate": [
        "2012-02-25(中国香港)"
    ],
    "this_title": [
        "千奇百趣高B班"
    ],
    "douban_link": "https://movie.douban.com/subject/26967945/",
    "trans_title": [
        "Neighborhood Treasures 4"
    ],
    "douban_votes": "0",
    "introduction": "节目主持为森美、阮小仪，助手为李伟健（粉笔）及陈亭嘉（粉刷）。至于旁白，本辑除了林保全及雷碧娜外，亦有使用其他配音演员（全为男性路人，而女性路人和小孩则由雷碧娜负责），当中包括陈永信、李锦纶、梁伟德、招世亮、朱子聪、叶振声、刘昭文、陈欣、萧徽勇。本节目是该台早前播出之《千奇百趣》系列之第六辑，以课室为主题，奇趣内容关于日本境内的奇景。节目于2012年2月25日至2012年6月16日，逢星期六香港时间20:30-21:30于翡翠台、",
    "chinese_title": "千奇百趣高B班",
    "douban_rating": "0/10 from 0 users",
    "foreign_title": "",
    "douban_rating_average": 0,
    "update_at": "2025-06-07T10:01:09"
}