{
    "aka": [
        "新版机器战警",
        "新版铁甲威龙",
        "机器战警(台)",
        "铁甲威龙(港)"
    ],
    "sid": "3077742",
    "cast": [
        {
            "url": "/celebrity/1036743/",
            "name": "乔尔·金纳曼 Joel Kinnaman",
            "@type": "Person"
        },
        {
            "url": "/celebrity/1010507/",
            "name": "加里·奥德曼 Gary Oldman",
            "@type": "Person"
        },
        {
            "url": "/celebrity/1049486/",
            "name": "迈克尔·基顿 Michael Keaton",
            "@type": "Person"
        },
        {
            "url": "/celebrity/1040985/",
            "name": "艾比·考尼什 Abbie Cornish",
            "@type": "Person"
        },
        {
            "url": "/celebrity/1009239/",
            "name": "杰基·厄尔·哈利 Jackie Earle Haley",
            "@type": "Person"
        },
        {
            "url": "/celebrity/1036428/",
            "name": "迈克尔·肯尼斯·威廉姆斯 Michael Kenneth Williams",
            "@type": "Person"
        },
        {
            "url": "/celebrity/1012506/",
            "name": "詹妮弗·艾莉 Jennifer Ehle",
            "@type": "Person"
        },
        {
            "url": "/celebrity/1002664/",
            "name": "杰伊·巴鲁切尔 Jay Baruchel",
            "@type": "Person"
        },
        {
            "url": "/celebrity/1055527/",
            "name": "玛丽安娜·琼-巴普蒂斯特 Marianne Jean-Baptiste",
            "@type": "Person"
        },
        {
            "url": "/celebrity/1054408/",
            "name": "塞缪尔·杰克逊 Samuel L. Jackson",
            "@type": "Person"
        },
        {
            "url": "/celebrity/1036540/",
            "name": "埃美·加西亚 Aimee Garcia",
            "@type": "Person"
        },
        {
            "url": "/celebrity/1299754/",
            "name": "道格拉斯·尤巴斯基 Douglas Urbanski",
            "@type": "Person"
        },
        {
            "url": "/celebrity/1320447/",
            "name": "约翰·保罗·卢腾 John Paul Ruttan",
            "@type": "Person"
        },
        {
            "url": "/celebrity/1338051/",
            "name": "帕特里克·加洛 Patrick Garrow",
            "@type": "Person"
        },
        {
            "url": "/celebrity/1338050/",
            "name": "克里斯·柯林斯 K.C. Collins",
            "@type": "Person"
        },
        {
            "url": "/celebrity/1108474/",
            "name": "丹尼尔·卡什 Daniel Kash",
            "@type": "Person"
        },
        {
            "url": "/celebrity/1099400/",
            "name": "扎克·格雷尼尔 Zach Grenier",
            "@type": "Person"
        },
        {
            "url": "/celebrity/1385660/",
            "name": "斯图尔特·阿诺特 Stewart Arnott",
            "@type": "Person"
        },
        {
            "url": "/celebrity/1327706/",
            "name": "梅兰妮·斯科洛凡诺 Melanie Scrofano",
            "@type": "Person"
        },
        {
            "url": "/celebrity/1178834/",
            "name": "马尔詹·奈沙特 Marjan Neshat",
            "@type": "Person"
        },
        {
            "url": "/celebrity/1133829/",
            "name": "科尔比·莫罗 Kirby Morrow",
            "@type": "Person"
        },
        {
            "url": "/celebrity/1274085/",
            "name": "乔丹 约翰孙-西德 Jordan Johnson-Hinds",
            "@type": "Person"
        },
        {
            "url": "/celebrity/1024056/",
            "name": "罗里·奥谢 Rory O&#39;Shea",
            "@type": "Person"
        },
        {
            "url": "/celebrity/1373238/",
            "name": "埃文·斯特恩 Evan Stern",
            "@type": "Person"
        },
        {
            "url": "/celebrity/1496843/",
            "name": "毛拉·格里尔森 Maura Grierson",
            "@type": "Person"
        },
        {
            "url": "/celebrity/1419464/",
            "name": "卡林·伯切尔 Carlyn Burchell",
            "@type": "Person"
        },
        {
            "url": "/celebrity/1449217/",
            "name": "菲利普·阿金 Philip Akin",
            "@type": "Person"
        }
    ],
    "site": "douban",
    "tags": [],
    "year": "2014",
    "genre": [
        "动作",
        "科幻",
        "犯罪"
    ],
    "awards": "",
    "poster": "https://img1.doubanio.com/view/photo/l_ratio_poster/public/p2170735207.jpg",
    "region": [
        "美国"
    ],
    "writer": [
        {
            "url": "/celebrity/1333974/",
            "name": "约书亚·祖特曼 Joshua Zetumer",
            "@type": "Person"
        },
        {
            "url": "/celebrity/1293076/",
            "name": "爱德华·诺麦尔 Edward Neumeier",
            "@type": "Person"
        },
        {
            "url": "/celebrity/1292161/",
            "name": "迈克尔·迈纳 Michael Miner",
            "@type": "Person"
        }
    ],
    "imdb_id": "tt1234721",
    "director": [
        {
            "url": "/celebrity/1023090/",
            "name": "何塞·帕迪里亚 José Padilha",
            "@type": "Person"
        }
    ],
    "duration": "117分钟(美国)",
    "episodes": "",
    "language": [
        "英语"
    ],
    "playdate": [
        "2014-02-12(美国)",
        "2014-02-28(中国大陆)"
    ],
    "imdb_link": "https://www.imdb.com/title/tt1234721/",
    "imdb_votes": 244991,
    "this_title": [
        "RoboCop"
    ],
    "douban_link": "https://movie.douban.com/subject/3077742/",
    "imdb_rating": "6.1/10 from 244991 users",
    "trans_title": [
        "机械战警",
        "新版机器战警",
        "新版铁甲威龙",
        "机器战警(台)",
        "铁甲威龙(港)"
    ],
    "douban_votes": "91366",
    "introduction": "2028年，专事军火开发的机器人公司Omni Corp.生产了大量装备精良的机械战警，他们被投入到维和和惩治犯罪等行动中，取得显著的效果。罪犯横行的底特律市，嫉恶如仇、正义感十足的警察亚历克斯·墨菲（乔尔·金纳曼 Joel Kinnaman 饰）遭到仇家暗算，身体受到毁灭性破坏。借助于Omni公司天才博士丹尼特·诺顿（加里·奥德曼 Gary Oldman 饰）最前沿的技术，墨菲以机械战警的形态复活。数轮严格的测试表明，墨菲足以承担起维护社会治安的重任，他的口碑在民众中直线飙升，而墨菲的妻子克拉拉（艾比·考尼什 Abbie Cornish 饰）和儿子大卫却再难从他身上感觉亲人的温暖。感知到妻儿的痛苦，墨菲决心向策划杀害自己的犯罪头子展开反击……",
    "chinese_title": "机械战警",
    "douban_rating": "6.4/10 from 91366 users",
    "foreign_title": "RoboCop",
    "imdb_rating_average": 6.1,
    "douban_rating_average": "6.4",
    "update_at": "2025-06-01T04:56:06"
}