{
    "aka": [
        "BLUE GIANT 藍色巨星(台)",
        "ブルージャイアント",
        "蓝色巨星(港)"
    ],
    "sid": "35634583",
    "cast": [
        {
            "url": "/celebrity/1314939/",
            "name": "山田裕贵 Yûki Yamada",
            "@type": "Person"
        },
        {
            "url": "/celebrity/1336215/",
            "name": "间宫祥太朗 Shotaro Mamiya",
            "@type": "Person"
        },
        {
            "url": "/celebrity/1337544/",
            "name": "冈山天音 Okayama Amane",
            "@type": "Person"
        }
    ],
    "site": "douban",
    "tags": [],
    "year": "2023",
    "genre": [
        "剧情",
        "动画",
        "音乐"
    ],
    "awards": "　　第47届日本电影学院奖(2024)\n　　最佳动画片(提名)\n　　最佳配乐 上原广美\n\n",
    "poster": "https://img9.doubanio.com/view/photo/l_ratio_poster/public/p2885199594.jpg",
    "region": [
        "日本"
    ],
    "writer": [
        {
            "url": "/celebrity/1510365/",
            "name": "石塚真一 Shin&#39;ichi Ishizuka",
            "@type": "Person"
        },
        {
            "url": "/celebrity/1510366/",
            "name": "NUMBER 8 NUMBER 8",
            "@type": "Person"
        }
    ],
    "imdb_id": "tt15737898",
    "director": [
        {
            "url": "/celebrity/1360044/",
            "name": "立川让 Yuzuru Tachikawa",
            "@type": "Person"
        }
    ],
    "duration": "120分钟",
    "episodes": "",
    "language": [
        "日语"
    ],
    "playdate": [
        "2023-02-17(日本)"
    ],
    "imdb_link": "https://www.imdb.com/title/tt15737898/",
    "imdb_votes": 1945,
    "this_title": [
        "BLUE GIANT"
    ],
    "douban_link": "https://movie.douban.com/subject/35634583/",
    "imdb_rating": "7.9/10 from 1945 users",
    "trans_title": [
        "蓝色巨人",
        "BLUE GIANT 藍色巨星(台)",
        "ブルージャイアント",
        "蓝色巨星(港)"
    ],
    "douban_votes": "6836",
    "introduction": "住在仙台的高中生・宫本大（山田裕贵 配音）深受爵士乐吸引，每天都独自在河边吹奏次中音萨克斯风。毕业后他来到东京，住进了高中同学・玉田俊二（冈山天音 配音）的公寓。某日，大在展演空间遇见同龄钢琴家・泽边雪祈（间宫祥太朗 配音），并邀请他共组乐团，受大影响而开始打鼓的玉田也加入组成3 人乐团“JASS”。连乐谱都看不懂，只是一心吹奏萨克斯风的大、从小就将一切献给爵士乐的雪祈、以及初学者玉田，以在日本最好的爵士乐具乐部表演并改变日本爵士乐风格为目标，尽全力投入在音乐活动之中。",
    "chinese_title": "蓝色巨人",
    "douban_rating": "8.2/10 from 6836 users",
    "foreign_title": "BLUE GIANT",
    "imdb_rating_average": 7.9,
    "douban_rating_average": "8.2",
    "update_at": "2024-06-21T19:00:10"
}