{
    "aka": [],
    "sid": "36621275",
    "cast": [
        {
            "url": "/celebrity/1341055/",
            "name": "阿加·达什 Agam Darshi",
            "@type": "Person"
        },
        {
            "url": "/celebrity/1032035/",
            "name": "丹尼尔·吉里斯 Daniel Gillies",
            "@type": "Person"
        },
        {
            "url": "/celebrity/1326081/",
            "name": "加洛德·约瑟夫 Jarod Joseph",
            "@type": "Person"
        },
        {
            "url": "/celebrity/1333900/",
            "name": "托尼·吉罗克斯 Tony Giroux",
            "@type": "Person"
        }
    ],
    "site": "douban",
    "tags": [],
    "year": "2024",
    "genre": [
        "剧情",
        "犯罪"
    ],
    "awards": "",
    "poster": "https://img1.doubanio.com/view/photo/l_ratio_poster/public/p2906851503.jpg",
    "region": [
        "加拿大"
    ],
    "writer": [],
    "imdb_id": "tt30487848",
    "director": [
        {
            "url": "/celebrity/1032535/",
            "name": "约翰·福西特 John Fawcett",
            "@type": "Person"
        }
    ],
    "duration": "",
    "episodes": "10",
    "language": [
        "英语"
    ],
    "playdate": [
        "2024-01-21(加拿大)"
    ],
    "imdb_link": "https://www.imdb.com/title/tt30487848/",
    "imdb_votes": 892,
    "this_title": [
        "Sight Unseen Season 1"
    ],
    "douban_link": "https://movie.douban.com/subject/36621275/",
    "imdb_rating": "6.2/10 from 892 users",
    "trans_title": [
        "拨云见日 第一季"
    ],
    "douban_votes": "0",
    "introduction": "Sight Unseen, in partnership with Bell Media’s CTV, follows Tess Avery (Dolly Lewis, The Dutchman’s Pipe), a top homicide detective who is forced to quit the job she loves after nearly killing her partner and being diagnosed as clinically blind. Reluctant to accept help, Tess uses an assistance app and connects with Sunny Patel (Agam Darshi, DMZ), a professional seeing-eye guid...",
    "chinese_title": "拨云见日 第一季",
    "douban_rating": "0/10 from 0 users",
    "foreign_title": "Sight Unseen Season 1",
    "imdb_rating_average": 6.2,
    "douban_rating_average": 0,
    "update_at": "2024-11-26T17:00:17"
}